awali_db_mapping-0.0.3.dist-info/licenses/LICENSE.txt
sql_schema_exporter/__init__.py
sql_schema_exporter/cli.py
sql_schema_exporter/core.py
sql_schema_exporter/lineage.py
awali_db_mapping-0.0.3.dist-info/METADATA
awali_db_mapping-0.0.3.dist-info/WHEEL
awali_db_mapping-0.0.3.dist-info/entry_points.txt
awali_db_mapping-0.0.3.dist-info/top_level.txt
awali_db_mapping-0.0.3.dist-info/RECORD
