Metadata-Version: 2.4
Name: awali_db_mapping
Version: 0.0.3
Summary: A short description of the awali_db_mapping package.
Author-email: Your Name <your@email.com>
License: Copyright (c) 2025 Awali Technologies, LLC. All rights reserved.
Project-URL: Homepage, https://github.com/AwaliTechnology/awali_db_mapping
Project-URL: Bug Tracker, https://github.com/AwaliTechnology/awali_db_mapping/issues
Classifier: Programming Language :: Python :: 3
Classifier: License :: Other/Proprietary License
Classifier: Operating System :: OS Independent
Requires-Python: >=3.8
License-File: LICENSE.txt
Dynamic: license-file
